diveplane/client/LICENSE-3RD-PARTY.txt
diveplane/client/__init__.py
diveplane/client/base.py
diveplane/client/cache.py
diveplane/client/client.py
diveplane/client/configuration.py
diveplane/client/exceptions.py
diveplane/client/protocols.py
diveplane/client/requirements-3.10.txt
diveplane/client/requirements-3.11.txt
diveplane/client/requirements-3.8.txt
diveplane/client/requirements-3.9.txt
diveplane/client/requirements-dev-3.10.txt
diveplane/client/requirements-dev-3.11.txt
diveplane/client/requirements-dev-3.8.txt
diveplane/client/requirements-dev-3.9.txt
diveplane/client/requirements-dev.in
diveplane/client/requirements.in
diveplane/client/pandas/__init__.py
diveplane/client/pandas/client.py
diveplane/client/tests/__init__.py
diveplane/client/tests/test_client.py
diveplane/client/tests/test_infer_feature_attributes.py
diveplane/client/tests/test_scikit.py
diveplane/direct/__init__.py
diveplane/direct/_utilities.py
diveplane/direct/client.py
diveplane/direct/core.py
diveplane/direct/tests/test_standalone.py
diveplane/reactor/__init__.py
diveplane/reactor/client.py
diveplane/reactor/project.py
diveplane/reactor/session.py
diveplane/reactor/trainee.py
diveplane/reactor/tests/conftest.py
diveplane/reactor/tests/test_reactor.py
diveplane/scikit/__init__.py
diveplane/scikit/scikit.py
diveplane/utilities/__init__.py
diveplane/utilities/eula_helper.py
diveplane/utilities/features.py
diveplane/utilities/guess_feature_attributes.py
diveplane/utilities/installation_verification.py
diveplane/utilities/internals.py
diveplane/utilities/json_wrapper.py
diveplane/utilities/locale.py
diveplane/utilities/monitors.py
diveplane/utilities/posix.py
diveplane/utilities/random.py
diveplane/utilities/utilities.py
diveplane/utilities/feature_attributes/__init__.py
diveplane/utilities/feature_attributes/base.py
diveplane/utilities/feature_attributes/infer_feature_attributes.py
diveplane/utilities/feature_attributes/pandas.py
diveplane/utilities/feature_attributes/protocols.py
diveplane_reactor_api-6.5.9.dist-info/LICENSE.txt
diveplane_reactor_api-6.5.9.dist-info/METADATA
diveplane_reactor_api-6.5.9.dist-info/WHEEL
diveplane_reactor_api-6.5.9.dist-info/entry_points.txt
diveplane_reactor_api-6.5.9.dist-info/top_level.txt
diveplane_reactor_api-6.5.9.dist-info/RECORD
